README
setup.py
django_pingback.egg-info/PKG-INFO
django_pingback.egg-info/SOURCES.txt
django_pingback.egg-info/dependency_links.txt
django_pingback.egg-info/requires.txt
django_pingback.egg-info/top_level.txt
pingback/__init__.py
pingback/admin.py
pingback/client.py
pingback/exceptions.py
pingback/managers.py
pingback/middleware.py
pingback/models.py
pingback/templatetags/__init__.py
pingback/templatetags/pingback_tags.py