Metadata-Version: 1.0
Name: django-pingback
Version: 0.1.4
Summary: Pingback client/server implementation for Django framework.
Home-page: http://hg.piranha.org.ua/django-pingback/
Author: Alexander Solovyov
Author-email: piranha@piranha.org.ua
License: New BSD License
Keywords: django apps
Platform: UNKNOWN
Classifier: Development Status :: 3 - Alpha
Classifier: Environment :: Plugins
Classifier: Framework :: Django
Classifier: Intended Audience :: Developers
Classifier: License :: OSI Approved :: BSD License
Classifier: Programming Language :: Python
Classifier: Topic :: Software Development :: Libraries :: Python Modules
